{
    "confInputs": {
        "ch1": {
            "contents": [
                "127.0.0.1",
                "56001"
            ],
            "tag": "UdpInUnicast"
        },
        "ch2": {
            "contents": [
                "127.0.0.1",
                "56002"
            ],
            "tag": "UdpInUnicast"
        },
        "ch3": {
            "contents": [
                "127.0.0.1",
                "56003"
            ],
            "tag": "UdpInUnicast"
        },
        "ch4": {
            "contents": [
                "127.0.0.1",
                "56004"
            ],
            "tag": "UdpInUnicast"
        },
        "čšžtest": {
            "contents": [
                "127.0.0.1",
                "56005"
            ],
            "tag": "UdpInUnicast"
        }
    },
    "confOutputFile": [
        "rec/recording",
        {
            "rotateKeep": 20,
            "rotateSizeMegaBytes": null,
            "rotateTimeHours": 0.5
        }
    ]
}
